<?xml version="1.0" encoding="UTF-8"?>
<particDesc xmlns="http://www.tei-c.org/ns/1.0">
 <listPerson>
  <person xml:id="L0205_M1">
   <persName type="role">Mr. Simon Swosser</persName>
   <persName type="spkr" n="34">SWOSSER.</persName>
  </person>
  <person xml:id="L0205_M2">
   <persName type="role">Captain Altamont Kidd</persName>
   <persName type="spkr" n="33">KIDD.</persName>
  </person>
  <person xml:id="L0205_M3">
   <persName type="role">Lieutenant Cornelius O'Pake</persName>
   <persName type="spkr" n="29">O'PAKE.</persName>
  </person>
  <person xml:id="L0205_M4">
   <persName type="role">Anthony Soskins</persName>
   <persName type="spkr" n="58">SOSKINS.</persName>
  </person>
  <person xml:id="L0205_M5">
   <persName type="role">John</persName>
   <persName type="spkr" n="14">JOHN.</persName>
  </person>
  <person xml:id="L0205_M6">
   <persName type="role">Butcher</persName>
   <persName type="spkr" n="3">BUTCHER.</persName>
  </person>
  <person xml:id="L0205_M7">
   <persName type="role">Baker</persName>
   <persName type="spkr" n="1">BAKER.</persName>
  </person>
  <person xml:id="L0205_M8">
   <persName type="role">Two Individuals</persName>
  </person>
  <person xml:id="L0205_F9">
   <persName type="role">Louisa Fitz-Johnson</persName>
   <persName type="spkr" n="99">LOUISA.</persName>
  </person>
  <person xml:id="L0205_F10">
   <persName type="role">Eliza Swosser</persName>
   <persName type="spkr" n="61">ELIZA.</persName>
  </person>
  <person xml:id="L0205_F11">
   <persName type="role">Sally</persName>
   <persName type="spkr" n="4">SALLY.</persName>
  </person>
  <person xml:id="L0205_mult">
   <persName type="role">[Multiple speakers]</persName>
   <persName type="spkr">KIDD.|SOSKINS</persName>
  </person>
 </listPerson>
</particDesc>
